_paddlespeech_ctcdecoders.cpython-38-x86_64-linux-gnu.so
paddlespeech_ctcdecoders.py
paddlespeech_ctcdecoders-0.2.1.dist-info/COPYING.APACHE2.0
paddlespeech_ctcdecoders-0.2.1.dist-info/COPYING.LESSER.3
paddlespeech_ctcdecoders-0.2.1.dist-info/LICENSE
paddlespeech_ctcdecoders-0.2.1.dist-info/METADATA
paddlespeech_ctcdecoders-0.2.1.dist-info/WHEEL
paddlespeech_ctcdecoders-0.2.1.dist-info/top_level.txt
paddlespeech_ctcdecoders-0.2.1.dist-info/RECORD
