Metadata-Version: 2.1
Name: paddlespeech-ctcdecoders
Version: 0.2.1
Summary: CTC decoders in paddlespeech
Home-page: https://github.com/PaddlePaddle/PaddleSpeech
Author: PaddlePaddle Speech and Language Team
Author-email: paddlesl@baidu.com
License: Apache 2.0, GNU Lesser General Public License v3 (LGPLv3) (LGPL-3)
Platform: UNKNOWN
License-File: LICENSE
License-File: COPYING.APACHE2.0
License-File: COPYING.LESSER.3
